{"firstname":"","lastname":"","race":"","class":"","class2":"","sex":"","age":"","align":"","statRolls":"0","hp":"","maxHp":"","restMode":"0","stats":{"Strength":"1","Dexterity":"1","Constitution":"1","Intelligence":"1","Wisdom":"1","Charisma":"1"},"gold":"0","exp":"0","inv":{"Helm":"","Necklace":"","Chest":"","Legs":"","Gauntlets":"","Boots":"","Left Ring":"","Right Ring":"","Main Hand":"","Off Hand":"","Quiver":""},"traits":[],"skills":[],"spells":[{"l1":[],"l2":[],"l3":[],"l4":[],"l5":[],"l6":[],"l7":[],"l8":[],"l9":[]}],"notes":[],"bag":[]}
